{
  "foodItem": [
    {
      "name": "El Tren De Villa",
      "type": "Mexican",
      "location": "95 E Main St, Mohawk, NY",
      "town": "Mohawk, NY",
      "hours": "",
      "cost": "Inexpensive to Moderate",
      "description": "",
      "phoneNumber": "315-210-4040",
      "image": {
        "first": "el-tren-de-villa",
        "second": "el-tren-de-villa-2",
        "third": "el-tren-de-villa-3",
        "fourth": "el-tren-de-villa-4",
        "fifth": "el-tren-de-villa-5" }, 
      "url": "",
      "highlight": false,
      "rating": 4.5,
      "isExpanded": false
    },
    {
      "name": "Crazy Otto's Empire Diner",
      "type": "American",
      "location": "100 W Albany St, Herkimer, NY",
      "town": "Herkimer, NY",
      "hours": "",
      "cost": "Moderate",
      "description": "",
      "phoneNumber": "315-866-8801",
      "image": {
        "first": "crazy-ottos",
        "second": "crazy-ottos-2",
        "third": "crazy-ottos-3",
        "fourth": "crazy-ottos-4",
        "fifth": "crazy-ottos-5" },
      "url": "",
      "highlight": false,
      "rating": 4.6,
      "isExpanded": false
    },
    {
      "name": "Ann Street Restaurant & Deli",
      "type": "American",
      "location": "381 S Ann St, Little Falls",
      "town": "Little Falls, NY",
      "hours": "",
      "cost": "Inexpensive to Moderate",
      "description": "",
      "phoneNumber": "315-823-3290",
      "image": {
        "first": "ann-st-restaurant",
        "second": "ann-st-restaurant-2",
        "third": "ann-st-restaurant-3",
        "fourth": "ann-st-restaurant-4",
        "fifth": "ann-st-restaurant-5" },
      "url": "",
      "highlight": false,
      "rating": 4.6,
      "isExpanded": false
    },
    {
      "name": "Canal Side Inn",
      "type": "Fine Dining",
      "location": "395 Canal Pl, Little Falls, NY",
      "town": "Little Falls, NY",
      "hours": "",
      "cost": "Moderate to Expensive",
      "description": "",
      "phoneNumber": "315-823-1170",
      "image": {
        "first": "",
        "second": "",
        "third": "",
        "fourth": "",
        "fifth": "" },
      "url": "",
      "highlight": false,
      "rating": 4.5,
      "isExpanded": false
    },
    {
      "name": "Ed's Pizza Place",
      "type": "Italian",
      "location": "532 E Main St, Little Falls, NY",
      "town": "Little Falls, NY",
      "hours": "",
      "cost": "Inexpensive to Moderate",
      "description": "Delivery, Takeout or Dine-In. One of the best pizza places in the area!",
      "phoneNumber": "315-823-0476",
      "image": {
        "first": "eds-pizza-menu",
        "second": "",
        "third": "",
        "fourth": "",
        "fifth": "" },
      "url": "",
      "highlight": false,
      "rating": 4.5,
      "isExpanded": false
    },
    {
      "name": "The Renaissance Pub",
      "type": "Bar",
      "location": "550 E Main St",
      "town": "Little Falls, NY",
      "hours": "",
      "cost": "",
      "description": "",
      "phoneNumber": "315-556-1006",
      "image": {
        "first": "",
        "second": "",
        "third": "",
        "fourth": "",
        "fifth": "" }, 
      "url": "",
      "highlight": false,
      "rating": 4.5,
      "isExpanded": false
    },
    {
      "name": "Fat Cats",
      "type": "Seafood",
      "location": "200 King St, Herkimer, NY",
      "town": "Herkimer, NY",
      "hours": "",
      "cost": "Inexpensive to Moderate",
      "description": "",
      "phoneNumber": "315-866-5716",
      "image": {
        "first": "fat-cats",
        "second": "fat-cats-2",
        "third": "fat-cats-3",
        "fourth": "fat-cats-4",
        "fifth": "fat-cats-5" },
      "url": "",
      "highlight": false,
      "rating": 4.6,
      "isExpanded": false
    },
    {
      "name": "Beardslee Castle",
      "type": "American",
      "location": "123 Old State Rd",
      "town": "Little Falls, NY",
      "hours": "",
      "cost": "Moderate to Expensive",
      "description": "Inspired American Cuisine in a magnificent setting. Built in 1860 as a replica of an Irish Castle, Beardslee Castle is at once both modern and ancient... with the finest in creative cuisine, memorable wedding receptions banquets and special events.",
      "phoneNumber": "315-823-3000",
      "image": {
        "first": "beardslee-castle",
        "second": "beardslee-castle-2",
        "third": "beardslee-castle-3",
        "fourth": "beardslee-castle-4",
        "fifth": "beardslee-castle-5" }, 
      "url": "http://beardsleecastle.com/",
      "highlight": false,
      "rating": 4.6,
      "isExpanded": false
    },
    {
      "name": "Ruggiero's Trattoria",
      "type": "Italian",
      "location": "122 W Main St",
      "town": "Little Falls, NY",
      "hours": "",
      "cost": "Moderate",
      "description": "",
      "phoneNumber": "315-823-1414",
      "image": {
        "first": "ruggieros-trattoria",
        "second": "ruggieros-trattoria-2",
        "third": "ruggieros-trattoria-3",
        "fourth": "ruggieros-trattoria-4",
        "fifth": "ruggieros-trattoria-5" },
      "url": "",
      "highlight": false,
      "rating": 4.3,
      "isExpanded": false
    },
    {
      "name": "Yetty's Pizza",
      "type": "Italian",
      "location": "109 Mohawk St, Herkimer, NY",
      "town": "Herkimer, NY",
      "hours": "",
      "cost": "Inexpensive to Moderate",
      "description": "",
      "phoneNumber": "315-866-4201",
      "image": {
        "first": "yettys-pizza",
        "second": "yettys-pizza-2",
        "third": "yettys-pizza-3",
        "fourth": "yettys-pizza-4",
        "fifth": "yettys-pizza-5" },
      "url": "https://www.yettys.com",
      "highlight": false,
      "rating": 4.2,
      "isExpanded": false
    },
    {
      "name": "Sorrento Pizzeria & Restaurant",
      "type": "Italian",
      "location": "86 Central Plaza, Ilion, NY",
      "town": "Ilion, NY",
      "hours": "",
      "cost": "Moderate",
      "description": "",
      "phoneNumber": "315-894-9991",
      "image": {
        "first": "sorrento-pizzeria",
        "second": "sorrento-pizzeria-2",
        "third": "sorrento-pizzeria-3",
        "fourth": "sorrento-pizzeria-4",
        "fifth": "sorrento-pizzeria-5" },
      "url": "",
      "highlight": false,
      "rating": 4.2,
      "isExpanded": false
    },
    {
      "name": "Tokyo Sushi",
      "type": "Japanese",
      "location": "100 N Caroline St, Herkimer, NY",
      "town": "Herkimer, NY",
      "hours": "",
      "cost": "Moderate",
      "description": "",
      "phoneNumber": "315-866-8899",
      "image": {
        "first": "tokyo-sushi",
        "second": "tokyo-sushi-2",
        "third": "tokyo-sushi-3",
        "fourth": "tokyo-sushi-4",
        "fifth": "tokyo-sushi-5" },
      "url": "https://tokyosushinytogo.com/",
      "rating": 4.5,
      "highlight": false,
      "isExpanded": false
    }
  ]
}
